mcp_playwright/__init__.py
mcp_playwright/server.py
mcp_playwright/core/__init__.py
mcp_playwright/core/browser_manager.py
mcp_playwright/tools/__init__.py
mcp_playwright/tools/browser_tools.py
mcp_playwright-0.1.1.dist-info/METADATA
mcp_playwright-0.1.1.dist-info/WHEEL
mcp_playwright-0.1.1.dist-info/entry_points.txt
mcp_playwright-0.1.1.dist-info/licenses/LICENSE
mcp_playwright-0.1.1.dist-info/RECORD
