Metadata-Version: 2.4
Name: mcp-playwright
Version: 0.1.1
Summary: 基于Playwright的模型上下文协议(MCP)服务器，为AI助手提供强大的浏览器自动化能力
Project-URL: Homepage, https://github.com/ma-pony/mcp-playwright
Project-URL: Repository, https://github.com/ma-pony/mcp-playwright
Project-URL: Documentation, https://github.com/ma-pony/mcp-playwright#readme
Project-URL: Bug Tracker, https://github.com/ma-pony/mcp-playwright/issues
Project-URL: Changelog, https://github.com/ma-pony/mcp-playwright/releases
Author-email: ma-pony <mtf201013@gmail.com>
License: MIT
License-File: LICENSE
Keywords: ai,automation,browser,fastmcp,llm,mcp,playwright
Classifier: Development Status :: 4 - Beta
Classifier: Intended Audience :: Developers
Classifier: License :: OSI Approved :: MIT License
Classifier: Programming Language :: Python :: 3
Classifier: Programming Language :: Python :: 3.10
Classifier: Programming Language :: Python :: 3.11
Classifier: Programming Language :: Python :: 3.12
Classifier: Topic :: Internet :: WWW/HTTP :: Browsers
Classifier: Topic :: Scientific/Engineering :: Artificial Intelligence
Classifier: Topic :: Software Development :: Libraries :: Python Modules
Classifier: Topic :: Software Development :: Testing
Requires-Python: >=3.10
Requires-Dist: mcp[cli]>=1.9.0
Requires-Dist: patchright>=1.52.0
Requires-Dist: playwright>=1.52.0
